{
  "id": "d1571493-1f40-4ad3-8d47-2e7f4d8f0d54",
  "prevId": "3a8755e1-c960-4311-8162-e2eb7bdfe71a",
  "version": "7",
  "dialect": "postgresql",
  "tables": {
    "nlw_pocket.goal_completions": {
      "name": "goal_completions",
      "schema": "nlw_pocket",
      "columns": {
        "id": {
          "name": "id",
          "type": "text",
          "primaryKey": true,
          "notNull": true
        },
        "goal_id": {
          "name": "goal_id",
          "type": "text",
          "primaryKey": false,
          "notNull": true
        },
        "created_at": {
          "name": "created_at",
          "type": "timestamp with time zone",
          "primaryKey": false,
          "notNull": true,
          "default": "now()"
        }
      },
      "indexes": {},
      "foreignKeys": {
        "goal_completions_goal_id_goals_id_fk": {
          "name": "goal_completions_goal_id_goals_id_fk",
          "tableFrom": "goal_completions",
          "tableTo": "goals",
          "schemaTo": "nlw_pocket",
          "columnsFrom": [
            "goal_id"
          ],
          "columnsTo": [
            "id"
          ],
          "onDelete": "no action",
          "onUpdate": "no action"
        }
      },
      "compositePrimaryKeys": {},
      "uniqueConstraints": {}
    },
    "nlw_pocket.goals": {
      "name": "goals",
      "schema": "nlw_pocket",
      "columns": {
        "id": {
          "name": "id",
          "type": "text",
          "primaryKey": true,
          "notNull": true
        },
        "title": {
          "name": "title",
          "type": "text",
          "primaryKey": false,
          "notNull": true
        },
        "desired_weekly_frequency": {
          "name": "desired_weekly_frequency",
          "type": "integer",
          "primaryKey": false,
          "notNull": true
        },
        "created_at": {
          "name": "created_at",
          "type": "timestamp with time zone",
          "primaryKey": false,
          "notNull": true,
          "default": "now()"
        }
      },
      "indexes": {},
      "foreignKeys": {},
      "compositePrimaryKeys": {},
      "uniqueConstraints": {}
    }
  },
  "enums": {},
  "schemas": {
    "nlw_pocket": "nlw_pocket"
  },
  "sequences": {},
  "_meta": {
    "columns": {},
    "schemas": {},
    "tables": {}
  }
}